LICENSE
MANIFEST.in
README.md
__init__.py
flow_field.py
flow_utils.py
map_utils.py
mesh.py
pyproject.toml
setup.cfg
stitch_elastic.py
stitch_rigid.py
warp.py
sofima.egg-info/PKG-INFO
sofima.egg-info/SOURCES.txt
sofima.egg-info/dependency_links.txt
sofima.egg-info/requires.txt
sofima.egg-info/top_level.txt