Metadata-Version: 2.1
Name: sofima
Version: 0.1
Summary: Scalable Optical Flow-based Image Montaging and Alignment
Home-page: https://github.com/google-research/sofima
Author: Michal Januszewski
Author-email: mjanusz@google.com
License: UNKNOWN
Project-URL: Bug Tracker, https://github.com/google-research/sofima/issues
Platform: UNKNOWN
Classifier: Programming Language :: Python :: 3
Classifier: License :: OSI Approved :: Apache Software License
Classifier: Operating System :: OS Independent
Requires-Python: >=3.6
License-File: LICENSE
